cr_api_client/__init__.py
cr_api_client/cli_parser/provisioning_parser.py
cr_api_client/config.py
cr_api_client/core_api.py
cr_api_client/cyber_range.py
cr_api_client/logger.py
cr_api_client/provisioning_api.py
cr_api_client/redteam_api.py
cr_api_client/topology/TopologyElements.py
cr_api_client/topology/TopologyGenerator.py
cr_api_client/topology/TopologyLinksGenerator.py
cr_api_client/topology/TopologyNodeGenerator.py
cr_api_client/topology/TopologyNodesGenerator.py
cr_api_client/user_activity_api.py
cr_api_client/yaml_helper.py
cr_api_client-5.0.23.dist-info/AUTHORS
cr_api_client-5.0.23.dist-info/LICENSE
cr_api_client-5.0.23.dist-info/METADATA
cr_api_client-5.0.23.dist-info/WHEEL
cr_api_client-5.0.23.dist-info/entry_points.txt
cr_api_client-5.0.23.dist-info/RECORD
